Workbook

Sheet Cover
A1: NTAP Cost Scenarios - Grounded Model | J1: Scenario margin comparison
A2: Inpatient launch economics, NTAP bridge mechanics, and whole-episode spend in one source-grounded workbook.
A3: Built from CMS and source materials in the workbook. Blue cells elsewhere are editable inputs; gray cells are formulas.
A5: Technology price / low | C5: NTAP percentage | E5: No NTAP margin | G5: Episode delta
A6: =Inputs!B4 -> 25000 | C6: =Inputs!B16 -> 0.65 | E6: =Scenario_No_NTAP!B8 -> -15000 | G6: =Episode_Total_Care!D15 -> -4350
A8: User prompt anchor | C8: CMS policy reference | E8: Bundled DRG absorption | G8: Payer-visible spend change
A10: What it shows | E10: Decision use
A11: The workbook separates the DRG payment problem, the NTAP bridge, and the post-reweighting state. It shows how much of the margin story is driven by the product price versus the bundled facility economics around ICU days, floor days, ancillary services, and post-acute utilization. | E11: Use the model to compare no-NTAP, NTAP bridge, and post-NTAP economics; test whole-episode savings assumptions; and anchor launch discussions in payment mechanics instead of generic access language.
A18: Scenario snapshot | E18: Key readout
A19: Scenario | B19: DRG margin | C19: NTAP / delta | D19: Episode spend | E19: NTAP does not erase the bundled-payment problem; it bridges the initial launch period while the case economics and DRG weights catch up. The episode spend block shows whether product uptake improves the payer lens even when the hospital lens remains tight.
A20: No NTAP | B20: =Scenario_No_NTAP!B8 -> -15000 | C20: - | D20: =Episode_Total_Care!B15 -> 65500
A21: NTAP bridge | B21: =Scenario_NTAP!B9 -> -5250 | C21: =Scenario_NTAP!B8 -> 9750 | D21: =Episode_Total_Care!C15 -> 61150
A22: Post-DRG | B22: =Scenario_Post_DRG!B8 -> 5000 | C22: - | D22: =Price_Ladder!E4 -> 65500
A23: Navigation
A24: [Inputs] | C24: Editable assumptions and linked inputs | J24: Scenario | K24: Margin ($)
A25: [Episode_Cost_Breakdown] | C25: Bundled vs non-bundled episode components | J25: No NTAP | K25: =Scenario_No_NTAP!B8 -> -15000
A26: [Scenario_No_NTAP] | C26: Baseline DRG absorption | J26: NTAP bridge | K26: =Scenario_NTAP!B9 -> -5250
A27: [Scenario_NTAP] | C27: NTAP bridge comparison | J27: Post-DRG | K27: =Scenario_Post_DRG!B8 -> 5000
A28: [Episode_Total_Care] | C28: Whole-episode payer lens
A29: [Sensitivity] | C29: Price sensitivity grids
A30: [Price_Ladder] | C30: DRG margin and episode spend ladder
A31: [DRG_Definitions] | C31: DRG reference titles
A32: [Sources] | C32: Source index

Sheet Inputs
A1: NTAP Cost Model Inputs (Product X)
A3: Input | B3: Value | C3: Notes
A4: Technology price - low | B4: 25000 | C4: User assumption (question prompt)
A5: Technology price - mid | B5: 35000 | C5: User assumption (question prompt)
A6: Technology price - high | B6: 50000 | C6: User assumption (question prompt)
A7: DRG payment anchor - low | B7: 30000 | C7: Midpoint anchor from user-provided DRG ranges
A8: DRG payment anchor - high | B8: 50000 | C8: Upper anchor from user-provided DRG ranges
A9: MS-DRG 023 range low | B9: 35000 | C9: User assumption (question prompt)
A10: MS-DRG 023 range high | B10: 50000 | C10: User assumption (question prompt)
A11: MS-DRG 024 range low | B11: 25000 | C11: User assumption (question prompt)
A12: MS-DRG 024 range high | B12: 35000 | C12: User assumption (question prompt)
A13: Other facility costs (bundled DRG) | B13: =Episode_Cost_Breakdown!E11 -> 20000 | C13: Linked bundled-facility subtotal from episode sheet
A14: Baseline LOS (days) | B14: 7 | C14: User assumption: baseline 6 to 8 days
A15: Baseline ICU days | B15: 3 | C15: User assumption: baseline 2 to 4 days
A16: NTAP percentage | B16: 0.65 | C16: CMS NTAP policy reference [1]
A17: Post-DRG payment scenario | B17: 50000 | C17: Illustrative post-reweighting payment anchor

Sheet Episode_Cost_Breakdown
A1: Episode Cost Components - Classified
A3: Category | B3: What it comes from | C3: How it is paid | D3: Illustrative math | E3: Amount
A4: ICU / neuro-ICU monitoring, nursing, telemetry | B4: Intensive days cost center; 2-4 ICU days in the Product X materials, with ICU costs of roughly $3K-$5K per day. | C4: Bundled into the inpatient MS-DRG under IPPS; may be offset by an outlier payment if the case exceeds the fixed-loss threshold. | D4: 3 days x $4,000/day | E4: 12000
A5: Routine floor days, room and board, standard nursing | B5: Routine days cost center; the remainder of the 6-8 day hospital stay after ICU time. | C5: Bundled into the inpatient MS-DRG under IPPS; not a separate hospital line item. | D5: 4 days x $1,250/day | E5: 5000
A6: Ancillary hospital services, pharmacy, supplies, case management | B6: Imaging, labs, bag changes, supply handling, and discharge coordination described in the Product X materials. | C6: Bundled into the inpatient MS-DRG under IPPS. | D6: Illustrative residual allocation | E6: 3000
A7: Physician professional services = per CPT Payment = (Total RVUs} *{Conversion Factor} | B7: Hospitalist, neurologist, interventional and consult services. | C7: Paid separately under the Physician Fee Schedule / Part B. | D7: Episode-level component; outside hospital DRG margin | E7: 3500
A8: Post-acute care after discharge | B8: SNF, IRF, HHA, LTCH services after the index stay. | C8: Paid under separate PPSs outside the index DRG. | D8: Episode-level component; outside hospital DRG margin | E8: 14000
A9: Readmissions / ED revisit in 90-day window | B9: Unplanned post-discharge acute utilization attributable to recurrent events or complications. | C9: Paid as separate claims across facility/professional settings. | D9: Episode-level component; outside index DRG margin | E9: 6000
A10: Long-term support and disability-related care (blended expected value) | B10: Expected-value allocation for custodial/supportive services in poor functional recovery states. | C10: Paid across post-acute and community support channels (payer-dependent). | D10: Episode-level component; outside index DRG margin | E10: 12000
D11: Bundled facility subtotal (used in DRG-margin scenarios) | E11: =SUM(E4:E6) -> 20000
D12: Non-facility subtotal (payer episode lens) | E12: =SUM(E7:E10) -> 35500
D13: Total non-drug episode costs | E13: =SUM(E4:E10) -> 55500
A14: Note | B14: DRG margin scenarios use only the bundled facility subtotal. Episode-total scenarios include professional, post-acute, readmission, and long-term support components to capture payer-visible spend.

Sheet Scenario_No_NTAP
A1: Scenario 1 - No NTAP
A3: Metric | B3: Value
A4: DRG payment | B4: =Inputs!B7 -> 30000
A5: Product X cost | B5: =Inputs!B4 -> 25000
A6: Other costs | B6: =Inputs!B13 -> 20000
A7: Total cost | B7: =B5+B6 -> 45000
A8: Margin (no NTAP) | B8: =B4-B7 -> -15000
A9: Interpretation | B9: Negative margin indicates full absorption by hospital under bundled DRG payment.

Sheet Scenario_NTAP
A1: Scenario 2 - NTAP Bridge
A3: Metric | B3: Policy-Consistent | C3: Simplified Planning
A4: DRG payment | B4: =Inputs!B7 -> 30000 | C4: =Inputs!B7 -> 30000
A5: Product X cost | B5: =Inputs!B4 -> 25000 | C5: =Inputs!B4 -> 25000
A6: Other costs | B6: =Inputs!B13 -> 20000 | C6: =Inputs!B13 -> 20000
A7: Total cost | B7: =B5+B6 -> 45000 | C7: =C5+C6 -> 45000
A8: NTAP amount | B8: =MIN(B5*Inputs!B16,MAX(B7-B4,0)*Inputs!B16) -> 9750 | C8: =MIN(C5*Inputs!B16,MAX(C7-C4,0)) -> 15000
A9: Margin after NTAP | B9: =B4+B8-B7 -> -5250 | C9: =C4+C8-C7 -> 0
A11: Note | B11: Policy-consistent formula follows CMS language in [1]. | C11: Simplified planning formula mirrors common market shorthand.

Sheet Scenario_Post_DRG
A1: Scenario 3 - Post-NTAP / DRG Reweighting
A3: Metric | B3: Value
A4: DRG payment | B4: =Inputs!B17 -> 50000
A5: Product X cost | B5: =Inputs!B4 -> 25000
A6: Other costs | B6: =Inputs!B13 -> 20000
A7: Total cost | B7: =B5+B6 -> 45000
A8: Margin | B8: =B4-B7 -> 5000

Sheet Episode_Total_Care
A1: Whole-Episode Spend Model (Payer Lens)
A3: Assumption | B3: Value
A4: Base scenario: physician spend reduction | B4: 0.2
A5: Base scenario: post-acute spend reduction | B5: 0.4
A6: Base scenario: readmission/ED spend reduction | B6: 0.3
A7: Base scenario: long-term support reduction | B7: 0.5
A9: Component | B9: Baseline (No Product X) | C9: With Product X + NTAP Bridge | D9: Delta
A10: Index inpatient payment | B10: =Inputs!B7 -> 30000 | C10: =Inputs!B7+MIN(Inputs!B4*Inputs!B16,MAX((Inputs!B4+Inputs!B13)-Inputs!B7,0)*Inputs!B16) -> 39750 | D10: =C10-B10 -> 9750
A11: Physician professional services | B11: =Episode_Cost_Breakdown!E7 -> 3500 | C11: =ROUND(B11*(1-$B$4),0) -> 2800 | D11: =C11-B11 -> -700
A12: Post-acute care | B12: =Episode_Cost_Breakdown!E8 -> 14000 | C12: =ROUND(B12*(1-$B$5),0) -> 8400 | D12: =C12-B12 -> -5600
A13: Readmission and ED revisit | B13: =Episode_Cost_Breakdown!E9 -> 6000 | C13: =ROUND(B13*(1-$B$6),0) -> 4200 | D13: =C13-B13 -> -1800
A14: Long-term support / disability-related care | B14: =Episode_Cost_Breakdown!E10 -> 12000 | C14: =ROUND(B14*(1-$B$7),0) -> 6000 | D14: =C14-B14 -> -6000
A15: Total payer-visible episode spend | B15: =SUM(B10:B14) -> 65500 | C15: =SUM(C10:C14) -> 61150 | D15: =C15-B15 -> -4350
A17: Interpretation | B17: Base scenario only. Use Episode_Scenarios sheet for conservative/base/optimistic sensitivity.

Sheet Sensitivity
A1: Sensitivity Grid - Margin Without NTAP
A3: Price \ DRG | B3: 30000 | C3: 40000 | D3: 50000
A4: 25000 | B4: =B3-(A4+Inputs!B13) -> -15000 | C4: =C3-(A4+Inputs!B13) -> -5000 | D4: =D3-(A4+Inputs!B13) -> 5000
A5: 35000 | B5: =B3-(A5+Inputs!B13) -> -25000 | C5: =C3-(A5+Inputs!B13) -> -15000 | D5: =D3-(A5+Inputs!B13) -> -5000
A6: 50000 | B6: =B3-(A6+Inputs!B13) -> -40000 | C6: =C3-(A6+Inputs!B13) -> -30000 | D6: =D3-(A6+Inputs!B13) -> -20000
A8: Sensitivity Grid - Margin With Policy-Consistent NTAP
A10: Price \ DRG | B10: 30000 | C10: 40000 | D10: 50000
A11: 25000 | B11: =B10+MIN(A11*Inputs!B16,MAX((A11+Inputs!B13)-B10,0)*Inputs!B16)-(A11+Inputs!B13) -> -5250 | C11: =C10+MIN(A11*Inputs!B16,MAX((A11+Inputs!B13)-C10,0)*Inputs!B16)-(A11+Inputs!B13) -> -1750 | D11: =D10+MIN(A11*Inputs!B16,MAX((A11+Inputs!B13)-D10,0)*Inputs!B16)-(A11+Inputs!B13) -> 5000
A12: 35000 | B12: =B10+MIN(A12*Inputs!B16,MAX((A12+Inputs!B13)-B10,0)*Inputs!B16)-(A12+Inputs!B13) -> -8750 | C12: =C10+MIN(A12*Inputs!B16,MAX((A12+Inputs!B13)-C10,0)*Inputs!B16)-(A12+Inputs!B13) -> -5250 | D12: =D10+MIN(A12*Inputs!B16,MAX((A12+Inputs!B13)-D10,0)*Inputs!B16)-(A12+Inputs!B13) -> -1750
A13: 50000 | B13: =B10+MIN(A13*Inputs!B16,MAX((A13+Inputs!B13)-B10,0)*Inputs!B16)-(A13+Inputs!B13) -> -14000 | C13: =C10+MIN(A13*Inputs!B16,MAX((A13+Inputs!B13)-C10,0)*Inputs!B16)-(A13+Inputs!B13) -> -10500 | D13: =D10+MIN(A13*Inputs!B16,MAX((A13+Inputs!B13)-D10,0)*Inputs!B16)-(A13+Inputs!B13) -> -7000

Sheet DRG_Weights_Trend
A1: Stroke/EVT-Related MS-DRG Relative Weights (FY2020 to FY2026)
A3: FY | B3: 023 | C3: 024 | D3: 061 | E3: 062 | F3: 063 | G3: Source
A4: 2020 | B4: 5.6171 | C4: 4.0165 | D4: 2.7935 | E4: 2.0112 | F4: 1.6808 | G4: [13]
A5: 2021 | B5: 5.6623 | C5: 3.9325 | D5: 2.8882 | E5: 1.9872 | F5: 1.7099 | G5: [14]
A6: 2022 | B6: 5.6719 | C6: 3.939 | D6: 2.8912 | E6: 1.9883 | F6: 1.7097 | G6: [15]
A7: 2023 | B7: 5.7314 | C7: 3.9488 | D7: 2.9326 | E7: 1.9172 | F7: 1.581 | G7: [16]
A8: 2024 | B8: 5.6688 | C8: 3.7888 | D8: 2.8028 | E8: 1.8717 | F8: 1.4868 | G8: [17]
A9: 2025 | B9: 5.7047 | C9: 3.8014 | D9: 2.7032 | E9: 1.7808 | F9: 1.4047 | G9: [18]
A10: 2026 | B10: 5.7303 | C10: 3.9119 | D10: 2.7571 | E10: 1.7572 | F10: 1.4038 | G10: [19]

Sheet DRG_YoY_Change
A1: Annual YoY Change by DRG (FY2021 to FY2026)
A3: FY | B3: 023 | C3: 024 | D3: 061 | E3: 062 | F3: 063 | G3: Source
A4: 2021 | B4: 0.0080468569 | C4: -0.020913731 | D4: 0.033900125 | E4: -0.011933174 | F4: 0.017313184 | G4: [14]
A5: 2022 | B5: 0.0016954241 | C5: 0.0016528926 | D5: 0.0010387092 | E5: 0.00055354267 | F5: -0.0001169659 | G5: [15]
A6: 2023 | B6: 0.010490312 | C6: 0.0024879411 | D6: 0.014319314 | E6: -0.035759191 | F6: -0.075276364 | G6: [16]
A7: 2024 | B7: -0.010922288 | C7: -0.040518639 | D7: -0.044261065 | E7: -0.023732527 | F7: -0.059582543 | G7: [17]
A8: 2025 | B8: 0.00633291 | C8: 0.0033255912 | D8: -0.035535893 | E8: -0.048565475 | F8: -0.055219263 | G8: [18]
A9: 2026 | B9: 0.0044875278 | C9: 0.029068238 | D9: 0.019939331 | E9: -0.013252471 | F9: -0.0006407062 | G9: [19]

Sheet DRG_Definitions
A1: DRG Definitions Used in Stroke/EVT Modeling (FY 2026 titles)
A3: DRG | B3: FY 2026 title | C3: Source
A4: 023 | B4: CRANIOTOMY WITH MAJOR DEVICE IMPLANT OR ACUTE COMPLEX CNS PRINCIPAL DIAGNOSIS WITH MCC OR ANTINEOPLASTIC IMPLANT OR EPILEPSY WITH NEUROSTIMULATOR | C4: [19]
A5: 024 | B5: CRANIOTOMY WITH MAJOR DEVICE IMPLANT OR ACUTE COMPLEX CNS PRINCIPAL DIAGNOSIS WITHOUT MCC | C5: [19]
A6: 061 | B6: ISCHEMIC STROKE, PRECEREBRAL OCCLUSION OR TRANSIENT ISCHEMIA WITH THROMBOLYTIC AGENT WITH MCC | C6: [19]
A7: 062 | B7: ISCHEMIC STROKE, PRECEREBRAL OCCLUSION OR TRANSIENT ISCHEMIA WITH THROMBOLYTIC AGENT WITH CC | C7: [19]
A8: 063 | B8: ISCHEMIC STROKE, PRECEREBRAL OCCLUSION OR TRANSIENT ISCHEMIA WITH THROMBOLYTIC AGENT WITHOUT CC/MCC | C8: [19]
A10: Note | B10: DRGs listed here are directional comparators for payment-adequacy analysis, not a final Product X grouping determination.

Sheet Price_Ladder
A1: Price Ladder: DRG Margin and Whole-Episode Spend
A3: Product X Price | B3: DRG Margin (No NTAP) | C3: NTAP Amount | D3: DRG Margin (With NTAP) | E3: Baseline Episode Spend | F3: Episode Spend (With Product + NTAP) | G3: Episode Delta | H3: Interpretation
A4: 25000 | B4: =Inputs!B7-(25000+Inputs!B13) -> -15000 | C4: =MIN(25000*Inputs!B16,MAX((25000+Inputs!B13)-Inputs!B7,0)*Inputs!B16) -> 9750 | D4: =Inputs!B7+C4-(25000+Inputs!B13) -> -5250 | E4: =Inputs!B7+Episode_Cost_Breakdown!E7+Episode_Cost_Breakdown!E8+Episode_Cost_Breakdown!E9+Episode_Cost_Breakdown!E10 -> 65500 | F4: =Inputs!B7+C4+ROUND(Episode_Cost_Breakdown!E7*(1-Episode_Total_Care!B4),0)+ROUND(Episode_Cost_Breakdown!E8*(1-Episode_Total_Care!B5),0)+ROUND(Episode_Cost_Breakdown!E9*(1-Episode_Total_Care!B6),0)+ROUND(Episode_Cost_Breakdown!E10*(1-Episode_Total_Care!B7),0) -> 61150 | G4: =F4-E4 -> -4350 | H4: Negative episode delta = total episode savings
A5: 35000 | B5: =Inputs!B7-(35000+Inputs!B13) -> -25000 | C5: =MIN(35000*Inputs!B16,MAX((35000+Inputs!B13)-Inputs!B7,0)*Inputs!B16) -> 16250 | D5: =Inputs!B7+C5-(35000+Inputs!B13) -> -8750 | E5: =Inputs!B7+Episode_Cost_Breakdown!E7+Episode_Cost_Breakdown!E8+Episode_Cost_Breakdown!E9+Episode_Cost_Breakdown!E10 -> 65500 | F5: =Inputs!B7+C5+ROUND(Episode_Cost_Breakdown!E7*(1-Episode_Total_Care!B4),0)+ROUND(Episode_Cost_Breakdown!E8*(1-Episode_Total_Care!B5),0)+ROUND(Episode_Cost_Breakdown!E9*(1-Episode_Total_Care!B6),0)+ROUND(Episode_Cost_Breakdown!E10*(1-Episode_Total_Care!B7),0) -> 67650 | G5: =F5-E5 -> 2150 | H5: Negative episode delta = total episode savings
A6: 50000 | B6: =Inputs!B7-(50000+Inputs!B13) -> -40000 | C6: =MIN(50000*Inputs!B16,MAX((50000+Inputs!B13)-Inputs!B7,0)*Inputs!B16) -> 26000 | D6: =Inputs!B7+C6-(50000+Inputs!B13) -> -14000 | E6: =Inputs!B7+Episode_Cost_Breakdown!E7+Episode_Cost_Breakdown!E8+Episode_Cost_Breakdown!E9+Episode_Cost_Breakdown!E10 -> 65500 | F6: =Inputs!B7+C6+ROUND(Episode_Cost_Breakdown!E7*(1-Episode_Total_Care!B4),0)+ROUND(Episode_Cost_Breakdown!E8*(1-Episode_Total_Care!B5),0)+ROUND(Episode_Cost_Breakdown!E9*(1-Episode_Total_Care!B6),0)+ROUND(Episode_Cost_Breakdown!E10*(1-Episode_Total_Care!B7),0) -> 77400 | G6: =F6-E6 -> 11900 | H6: Negative episode delta = total episode savings
A8: Assumption note | B8: Price ladder uses the Base scenario from Episode_Scenarios. Optimistic long-term support avoidance is modeled sensitivity, not guaranteed outcome.

Sheet Episode_Scenarios
A1: Episode Savings Scenarios (Conservative / Base / Optimistic)
A3: Scenario | B3: Physician Reduction | C3: Post-Acute Reduction | D3: Readmission Reduction | E3: Long-Term Support Reduction | F3: Episode Delta @ $25K | G3: Episode Delta @ $35K | H3: Episode Delta @ $50K | I3: Notes
A4: Conservative | B4: 0.1 | C4: 0.2 | D4: 0.15 | E4: 0.25 | F4: =(Inputs!B7+MIN(25000*Inputs!B16,MAX((25000+Inputs!B13)-Inputs!B7,0)*Inputs!B16)+(ROUND(Episode_Cost_Breakdown!E7*(1-B4),0)+ROUND(Episode_Cost_Breakdown!E8*(1-C4),0)+ROUND(Episode_Cost_Breakdown!E9*(1-D4),0)+ROUND(Episode_Cost_Breakdown!E10*(1-E4),0)))-(Inputs!B7+Episode_Cost_Breakdown!E7+Episode_Cost_Breakdown!E8+Episode_Cost_Breakdown!E9+Episode_Cost_Breakdown!E10) -> 2700 | G4: =(Inputs!B7+MIN(35000*Inputs!B16,MAX((35000+Inputs!B13)-Inputs!B7,0)*Inputs!B16)+(ROUND(Episode_Cost_Breakdown!E7*(1-B4),0)+ROUND(Episode_Cost_Breakdown!E8*(1-C4),0)+ROUND(Episode_Cost_Breakdown!E9*(1-D4),0)+ROUND(Episode_Cost_Breakdown!E10*(1-E4),0)))-(Inputs!B7+Episode_Cost_Breakdown!E7+Episode_Cost_Breakdown!E8+Episode_Cost_Breakdown!E9+Episode_Cost_Breakdown!E10) -> 9200 | H4: =(Inputs!B7+MIN(50000*Inputs!B16,MAX((50000+Inputs!B13)-Inputs!B7,0)*Inputs!B16)+(ROUND(Episode_Cost_Breakdown!E7*(1-B4),0)+ROUND(Episode_Cost_Breakdown!E8*(1-C4),0)+ROUND(Episode_Cost_Breakdown!E9*(1-D4),0)+ROUND(Episode_Cost_Breakdown!E10*(1-E4),0)))-(Inputs!B7+Episode_Cost_Breakdown!E7+Episode_Cost_Breakdown!E8+Episode_Cost_Breakdown!E9+Episode_Cost_Breakdown!E10) -> 18950 | I4: Modest utilization shift
A5: Base | B5: 0.2 | C5: 0.4 | D5: 0.3 | E5: 0.5 | F5: =(Inputs!B7+MIN(25000*Inputs!B16,MAX((25000+Inputs!B13)-Inputs!B7,0)*Inputs!B16)+(ROUND(Episode_Cost_Breakdown!E7*(1-B5),0)+ROUND(Episode_Cost_Breakdown!E8*(1-C5),0)+ROUND(Episode_Cost_Breakdown!E9*(1-D5),0)+ROUND(Episode_Cost_Breakdown!E10*(1-E5),0)))-(Inputs!B7+Episode_Cost_Breakdown!E7+Episode_Cost_Breakdown!E8+Episode_Cost_Breakdown!E9+Episode_Cost_Breakdown!E10) -> -4350 | G5: =(Inputs!B7+MIN(35000*Inputs!B16,MAX((35000+Inputs!B13)-Inputs!B7,0)*Inputs!B16)+(ROUND(Episode_Cost_Breakdown!E7*(1-B5),0)+ROUND(Episode_Cost_Breakdown!E8*(1-C5),0)+ROUND(Episode_Cost_Breakdown!E9*(1-D5),0)+ROUND(Episode_Cost_Breakdown!E10*(1-E5),0)))-(Inputs!B7+Episode_Cost_Breakdown!E7+Episode_Cost_Breakdown!E8+Episode_Cost_Breakdown!E9+Episode_Cost_Breakdown!E10) -> 2150 | H5: =(Inputs!B7+MIN(50000*Inputs!B16,MAX((50000+Inputs!B13)-Inputs!B7,0)*Inputs!B16)+(ROUND(Episode_Cost_Breakdown!E7*(1-B5),0)+ROUND(Episode_Cost_Breakdown!E8*(1-C5),0)+ROUND(Episode_Cost_Breakdown!E9*(1-D5),0)+ROUND(Episode_Cost_Breakdown!E10*(1-E5),0)))-(Inputs!B7+Episode_Cost_Breakdown!E7+Episode_Cost_Breakdown!E8+Episode_Cost_Breakdown!E9+Episode_Cost_Breakdown!E10) -> 11900 | I5: Moderate utilization and discharge shift
A6: Optimistic | B6: 0.3 | C6: 0.7 | D6: 0.6 | E6: 1 | F6: =(Inputs!B7+MIN(25000*Inputs!B16,MAX((25000+Inputs!B13)-Inputs!B7,0)*Inputs!B16)+(ROUND(Episode_Cost_Breakdown!E7*(1-B6),0)+ROUND(Episode_Cost_Breakdown!E8*(1-C6),0)+ROUND(Episode_Cost_Breakdown!E9*(1-D6),0)+ROUND(Episode_Cost_Breakdown!E10*(1-E6),0)))-(Inputs!B7+Episode_Cost_Breakdown!E7+Episode_Cost_Breakdown!E8+Episode_Cost_Breakdown!E9+Episode_Cost_Breakdown!E10) -> -16700 | G6: =(Inputs!B7+MIN(35000*Inputs!B16,MAX((35000+Inputs!B13)-Inputs!B7,0)*Inputs!B16)+(ROUND(Episode_Cost_Breakdown!E7*(1-B6),0)+ROUND(Episode_Cost_Breakdown!E8*(1-C6),0)+ROUND(Episode_Cost_Breakdown!E9*(1-D6),0)+ROUND(Episode_Cost_Breakdown!E10*(1-E6),0)))-(Inputs!B7+Episode_Cost_Breakdown!E7+Episode_Cost_Breakdown!E8+Episode_Cost_Breakdown!E9+Episode_Cost_Breakdown!E10) -> -10200 | H6: =(Inputs!B7+MIN(50000*Inputs!B16,MAX((50000+Inputs!B13)-Inputs!B7,0)*Inputs!B16)+(ROUND(Episode_Cost_Breakdown!E7*(1-B6),0)+ROUND(Episode_Cost_Breakdown!E8*(1-C6),0)+ROUND(Episode_Cost_Breakdown!E9*(1-D6),0)+ROUND(Episode_Cost_Breakdown!E10*(1-E6),0)))-(Inputs!B7+Episode_Cost_Breakdown!E7+Episode_Cost_Breakdown!E8+Episode_Cost_Breakdown!E9+Episode_Cost_Breakdown!E10) -> -450 | I6: Long-term support modeled as full avoidance

Sheet Sources
A1: Public Sources Used
A3: Ref | B3: Topic | C3: URL
A4: [1] | B4: CMS New Medical Services and New Technologies (NTAP) page | C4: https://www.cms.gov/medicare/payment/prospective-payment-systems/acute-inpatient-pps/new-medical-services-and-new-technologies
A5: [2] | B5: FY 2027 NTAP application resources zip | C5: https://www.cms.gov/files/zip/fy2027ntapapplication-resources-reference-onlyzip.zip
A6: [3] | B6: MEARIS public resources | C6: https://mearis.cms.gov/public/resources
A7: [4] | B7: MEARIS public publications | C7: https://mearis.cms.gov/public/publications
A8: [5] | B8: Process for requesting new/revised ICD-10-PCS procedure codes | C8: https://www.cms.gov/medicare/coding-billing/icd-10-codes/process-for-requesting-new-revised-icd-10-pcs-procedure-codes
A9: [6] | B9: Acute Inpatient PPS landing page | C9: https://www.cms.gov/medicare/payment/prospective-payment-systems/acute-inpatient-pps
A10: [7] | B10: CMS guide for medical technology companies and other interested parties - IPPS | C10: https://www.cms.gov/cms-guide-medical-technology-companies-and-other-interested-parties/payment/ipps
A11: [8] | B11: CMS outlier payments page | C11: https://www.cms.gov/Medicare/Medicare-Fee-for-Service-Payment/AcuteInpatientPPS/outlier.html
A12: [9] | B12: Physician Fee Schedule | C12: https://www.cms.gov/cms-guide-medical-technology-companies-and-other-interested-parties/payment/physician-fee-schedule
A13: [10] | B13: Prospective Payment Systems - General Information | C13: https://www.cms.gov/medicare/payment/prospective-payment-systems
A14: [11] | B14: FY 2026 ICD-10-PCS code tables and index zip | C14: https://www.cms.gov/files/zip/2026-icd-10-pcs-code-tables-and-index.zip
... A27: [24] | B27: 2026 Official ICD-10-PCS Coding Guidelines | C27: https://www.cms.gov/files/document/2026-official-icd-10-pcs-coding-guidelines.pdf
