Workbook

Sheet Cover
A1: Provider Net Cost Model | J1: Annualized spread by scenario
A2: A provider economics model for WAC, 340B, Medicare, reimbursement timing, and operating margin under launch conditions.
A3: Built from the attached concept brief. Blue cells elsewhere are editable inputs; gray cells are formulas.
A5: WAC / dose | C5: 340B new-drug | E5: Medicare benchmark | G5: Base op margin / dose
A6: =Assumptions!B5 -> 39000 | C6: =Assumptions!B36 -> 29991 | E6: =Assumptions!B35 -> 40170 | G6: =OpMargin!B6 -> 750
A8: Launch anchor | C8: Ceiling-price estimate | E8: 103% of WAC | G8: No extra support
A10: What it shows | E10: Decision use
A11: This model translates payer mechanics into provider economics. It separates acquisition cost, reimbursement benchmarks, 340B pricing, cash timing, and operating friction so you can see where economics are thin, where they are favorable, and where support actually changes the outcome. | E11: Use the model to compare WAC, Medicare, and 340B economics; test how delay and support change the net margin; and explain why a site that looks viable on paper may still fail once denial drag, payment lag, or channel rules are applied.
A18: Annual WAC | C18: 340B spread / year | E18: Medicare spread / dose | G18: Payment speed cost / dose
A19: =Assumptions!B38 -> 1014000 | C19: =Assumptions!B45 -> 264654 | E19: =Assumptions!B35-Assumptions!B5 -> 1170 | G19: =Assumptions!B41 -> 384.65753
A22: Navigation
A23: [Assumptions] | C23: Editable inputs and derived values
A24: [DrugModel] | C24: Drug spread and 340B scenarios
A25: [OpMargin] | C25: Operating margin cases
A26: [Sensitivity] | C26: Support, delay, and revenue sensitivities
A27: [Sources] | C27: Plain-text source index

Sheet Assumptions
A1: Model Assumptions
A2: Blue cells are editable inputs. Gray cells are formulas. Comments point to the attached brief or public sources.
A4: Product and launch inputs
A5: WAC per dose | B5: 39000 | C5: $ / dose | D5: Launch anchor used throughout the brief.
A6: Administrations per year | B6: 26 | C6: doses / year | D6: Base annual utilization used in the scenario tables.
A7: Reference price haircut | B7: 0.15 | C7: % | D7: Used to create the 15% reference price.
A8: Reference price haircut | B8: 0.2 | C8: % | D8: Used to create the 20% reference price.
A9: Reference price haircut | B9: 0.3 | C9: % | D9: Used to create the 30% reference price.
A12: Policy and payment inputs
A13: Medicare benchmark uplift | B13: 0.03 | C13: % | D13: Medicare initial-sales benchmark used in the brief.
A14: 340B new-drug discount | B14: 0.231 | C14: % | D14: HRSA new-drug ceiling price estimate.
A15: 340B pediatric brand discount | B15: 0.171 | C15: % | D15: Alternative 340B estimate used in the brief.
A16: Denial drag rate | B16: 0.005 | C16: % | D16: Applied to total billed revenue in the operating model.
A17: Days to payment | B17: 45 | C17: days | D17: Used to estimate cash carrying cost.
A18: Annual carrying cost rate | B18: 0.08 | C18: % | D18: Used to estimate working-capital cost on drug acquisition.
A21: Operating inputs
A22: Procedure revenue per administration | B22: 750 | C22: $ / dose | D22: Procedure revenue assumption from the brief.
A23: Physician hours per dose | B23: 1.25 | C23: hours | D23: Time assumption used for the labor cost proxy.
A24: Physician hourly wage | B24: 98.97 | C24: $ / hour | D24: BLS pediatrician mean hourly wage used in the brief.
A25: Nurse hours per dose | B25: 3 | C25: hours | D25: Time assumption used for the labor cost proxy.
A26: Nurse hourly wage | B26: 50.21 | C26: $ / hour | D26: BLS registered nurse compensation proxy used in the brief.
A27: Commercial payer mix | B27: 0.5 | C27: % | D27: Internal mix assumption mentioned in the brief.
A28: Medicaid payer mix | B28: 0.5 | C28: % | D28: Internal mix assumption mentioned in the brief.
A31: Derived values
A32: 15% reference price | B32: =B5*(1-B7) -> 33150 | C32: $ / dose | D32: WAC less 15%.
A33: 20% reference price | B33: =B5*(1-B8) -> 31200 | C33: $ / dose | D33: WAC less 20%.
A34: 30% reference price | B34: =B5*(1-B9) -> 27300 | C34: $ / dose | D34: WAC less 30%.
A35: Medicare benchmark price | B35: =B5*(1+B13) -> 40170 | C35: $ / dose | D35: WAC at 103% of sales benchmark.
A36: 340B new-drug estimate | B36: =B5*(1-B14) -> 29991 | C36: $ / dose | D36: WAC less 23.1%.
A37: 340B pediatric estimate | B37: =B5*(1-B15) -> 32331 | C37: $ / dose | D37: WAC less 17.1%.
A38: Annual gross WAC | B38: =B5*B6 -> 1014000 | C38: $ / year | D38: Acquisition cost before any reimbursement.
A39: Labor cost per dose | B39: =B23*B24+B25*B26 -> 274.3425 | C39: $ / dose | D39: Physician plus nurse time proxy.
A40: Denial drag per dose | B40: =(B22+B5)*B16 -> 198.75 | C40: $ / dose | D40: 0.5% of total billed revenue.
A41: Payment speed cost per dose | B41: =B5*B18*B17/365 -> 384.65753 | C41: $ / dose | D41: Working-capital cost on WAC.
A42: 5% support per dose | B42: =B5*5% -> 1950 | C42: $ / dose | D42: Manufacturer support at 5% of WAC.
A43: 10% support per dose | B43: =B5*10% -> 3900 | C43: $ / dose | D43: Manufacturer support at 10% of WAC.
A44: 340B spread vs Medicare benchmark | B44: =B35-B36 -> 10179 | C44: $ / dose | D44: Drug payment benchmark minus new-drug 340B estimate.
A45: 340B annual spread | B45: =B44*B6 -> 264654 | C45: $ / year | D45: Annualized 340B spread at 26 doses.

Sheet DrugModel
A1: Drug Economics Model
A2: This sheet reproduces the scenario table in the brief and adds a small 340B estimate box.
A3: Scenario table
A5: Scenario | B5: Acquisition cost per dose | C5: 15% ref / dose | D5: 20% ref / dose | E5: 30% ref / dose | F5: Drug payment benchmark per dose | G5: Gross drug spread per dose | H5: Annualized spread at 26 doses | I5: Interpretation
A6: Commercial buy-and-bill at 100% of WAC | B6: =Assumptions!B5 -> 39000 | C6: =Assumptions!B32 -> 33150 | D6: =Assumptions!B33 -> 31200 | E6: =Assumptions!B34 -> 27300 | F6: =Assumptions!B5 -> 39000 | G6: =F6-B6 -> 0 | H6: =G6*Assumptions!B6 -> 0 | I6: Provider economics depend on procedure revenue, denial performance, and payment speed.
A7: Medicare Part B initial sales benchmark at 103% of WAC | B7: =Assumptions!B5 -> 39000 | C7: =Assumptions!B32 -> 33150 | D7: =Assumptions!B33 -> 31200 | E7: =Assumptions!B34 -> 27300 | F7: =Assumptions!B35 -> 40170 | G7: =F7-B7 -> 1170 | H7: =G7*Assumptions!B6 -> 30420 | I7: Public benchmark spread is thin before administration and rework cost are applied.
A8: 340B covered entity using the same 103% benchmark | B8: =Assumptions!B36 -> 29991 | C8: =Assumptions!B32 -> 33150 | D8: =Assumptions!B33 -> 31200 | E8: =Assumptions!B34 -> 27300 | F8: =Assumptions!B35 -> 40170 | G8: =F8-B8 -> 10179 | H8: =G8*Assumptions!B6 -> 264654 | I8: 340B changes provider economics immediately and materially.
A9: Commercial white-bagging | B9: =0 -> 0 | C9: =Assumptions!B32 -> 33150 | D9: =Assumptions!B33 -> 31200 | E9: =Assumptions!B34 -> 27300 | F9: =0 -> 0 | G9: =F9-B9 -> 0 | H9: =G9*Assumptions!B6 -> 0 | I9: The specialty pharmacy bills the plan directly, and the provider loses drug spread while retaining operational work.
A12: 340B estimate box
A13: Measure | B13: Per dose | C13: Discount vs WAC
A14: WAC | B14: =Assumptions!B5 -> 39000 | C14: =Assumptions!B5-Assumptions!B5 -> 0
A15: 340B new-drug estimate | B15: =Assumptions!B36 -> 29991 | C15: =Assumptions!B5-Assumptions!B36 -> 9009
A16: 340B pediatric estimate | B16: =Assumptions!B37 -> 32331 | C16: =Assumptions!B5-Assumptions!B37 -> 6669

Sheet OpMargin
A1: Operating Margin Model
A2: The base model keeps the acquisition/payment offset implicit and focuses on support, labor, denial, and cash timing.
A3: Base operating margin scenarios
A5: Scenario | B5: Procedure rev / dose | C5: Physician + nurse time / dose | D5: Denial drag / dose | E5: Payment speed cost / dose | F5: Manufacturer support / dose | G5: Net op margin / dose | H5: Annualized at 26 doses
A6: Commercial buy-and-bill, no extra support | B6: =Assumptions!B22 -> 750 | C6: =Assumptions!B39 -> 274.3425 | D6: =Assumptions!B40 -> 198.75 | E6: =Assumptions!B41 -> 384.65753 | F6: =0 -> 0 | G6: =B6-C6-D6-E6+F6 -> -107.75003 | H6: =G6*Assumptions!B6 -> -2801.5009
A7: Commercial buy-and-bill + 5.0% manufacturer discount or equivalent rebate | B7: =Assumptions!B22 -> 750 | C7: =Assumptions!B39 -> 274.3425 | D7: =Assumptions!B40 -> 198.75 | E7: =Assumptions!B41 -> 384.65753 | F7: =Assumptions!B42 -> 1950 | G7: =B7-C7-D7-E7+F7 -> 1842.25 | H7: =G7*Assumptions!B6 -> 47898.499
A8: Commercial buy-and-bill + 10.0% manufacturer discount or equivalent rebate | B8: =Assumptions!B22 -> 750 | C8: =Assumptions!B39 -> 274.3425 | D8: =Assumptions!B40 -> 198.75 | E8: =Assumptions!B41 -> 384.65753 | F8: =Assumptions!B43 -> 3900 | G8: =B8-C8-D8-E8+F8 -> 3792.25 | H8: =G8*Assumptions!B6 -> 98598.499
A11: Note: the support scenarios follow the brief. Drug spread is shown separately on DrugModel because, in the base buy-and-bill scenarios, acquisition cost and reimbursement offset each other.
A13: Cash exposure summary
A15: Measure | B15: Formula / basis | C15: Per dose | D15: Annualized
A16: Annual acquisition outlay at WAC | B16: WAC x doses | C16: =Assumptions!B5 -> 39000 | D16: =Assumptions!B5*Assumptions!B6 -> 1014000
A17: Annual reimbursement at Medicare benchmark | B17: 103% of WAC x doses | C17: =Assumptions!B35 -> 40170 | D17: =Assumptions!B35*Assumptions!B6 -> 1044420
A18: Annual 340B spread | B18: Benchmark less 340B estimate x doses | C18: =Assumptions!B44 -> 10179 | D18: =Assumptions!B45 -> 264654

Sheet Sensitivity
A1: Support, Delay, and Revenue Sensitivity
A2: The first table shows support sensitivity; the added sections below test payment delay and procedure revenue.
A3: Base operating margin remains the anchor; the new tables isolate one variable at a time.
A5: Support % | B5: Manufacturer support / dose | C5: Net op margin / dose | D5: Annualized at 26 doses | E5: Comment
A6: 0 | B6: =Assumptions!B5*A6 -> 0 | C6: =Assumptions!B22-Assumptions!B39-Assumptions!B40-Assumptions!B41+B6 -> -107.75003 | D6: =C6*Assumptions!B6 -> -2801.5009 | E6: Base scenario
A7: 0.01 | B7: =Assumptions!B5*A7 -> 390 | C7: =Assumptions!B22-Assumptions!B39-Assumptions!B40-Assumptions!B41+B7 -> 282.24997 | D7: =C7*Assumptions!B6 -> 7338.4991 | E7: Interpolated sensitivity
A8: 0.02 | B8: =Assumptions!B5*A8 -> 780 | C8: =Assumptions!B22-Assumptions!B39-Assumptions!B40-Assumptions!B41+B8 -> 672.24997 | D8: =C8*Assumptions!B6 -> 17478.499 | E8: Interpolated sensitivity
A9: 0.03 | B9: =Assumptions!B5*A9 -> 1170 | C9: =Assumptions!B22-Assumptions!B39-Assumptions!B40-Assumptions!B41+B9 -> 1062.25 | D9: =C9*Assumptions!B6 -> 27618.499 | E9: Interpolated sensitivity
A10: 0.04 | B10: =Assumptions!B5*A10 -> 1560 | C10: =Assumptions!B22-Assumptions!B39-Assumptions!B40-Assumptions!B41+B10 -> 1452.25 | D10: =C10*Assumptions!B6 -> 37758.499 | E10: Interpolated sensitivity
A11: 0.05 | B11: =Assumptions!B5*A11 -> 1950 | C11: =Assumptions!B22-Assumptions!B39-Assumptions!B40-Assumptions!B41+B11 -> 1842.25 | D11: =C11*Assumptions!B6 -> 47898.499 | E11: Brief scenario
A12: 0.06 | B12: =Assumptions!B5*A12 -> 2340 | C12: =Assumptions!B22-Assumptions!B39-Assumptions!B40-Assumptions!B41+B12 -> 2232.25 | D12: =C12*Assumptions!B6 -> 58038.499 | E12: Interpolated sensitivity
A13: 0.07 | B13: =Assumptions!B5*A13 -> 2730 | C13: =Assumptions!B22-Assumptions!B39-Assumptions!B40-Assumptions!B41+B13 -> 2622.25 | D13: =C13*Assumptions!B6 -> 68178.499 | E13: Interpolated sensitivity
A14: 0.08 | B14: =Assumptions!B5*A14 -> 3120 | C14: =Assumptions!B22-Assumptions!B39-Assumptions!B40-Assumptions!B41+B14 -> 3012.25 | D14: =C14*Assumptions!B6 -> 78318.499 | E14: Interpolated sensitivity
A15: 0.09 | B15: =Assumptions!B5*A15 -> 3510 | C15: =Assumptions!B22-Assumptions!B39-Assumptions!B40-Assumptions!B41+B15 -> 3402.25 | D15: =C15*Assumptions!B6 -> 88458.499 | E15: Interpolated sensitivity
A16: 0.1 | B16: =Assumptions!B5*A16 -> 3900 | C16: =Assumptions!B22-Assumptions!B39-Assumptions!B40-Assumptions!B41+B16 -> 3792.25 | D16: =C16*Assumptions!B6 -> 98598.499 | E16: Brief scenario
A19: Payment delay sensitivity
A20: Delay (days) | B20: Payment speed cost / dose | C20: Net op margin / dose | D20: Annualized at 26 doses | E20: Comment
A21: 0 | B21: =Assumptions!B5*Assumptions!B18*A21/365 -> 0 | C21: =Assumptions!B22-Assumptions!B39-Assumptions!B40-B21 -> 276.9075 | D21: =C21*Assumptions!B6 -> 7199.595 | E21: Higher delay raises working-capital drag
A22: 15 | B22: =Assumptions!B5*Assumptions!B18*A22/365 -> 128.21918 | C22: =Assumptions!B22-Assumptions!B39-Assumptions!B40-B22 -> 148.68832 | D22: =C22*Assumptions!B6 -> 3865.8964 | E22: Higher delay raises working-capital drag
A23: 30 | B23: =Assumptions!B5*Assumptions!B18*A23/365 -> 256.43836 | C23: =Assumptions!B22-Assumptions!B39-Assumptions!B40-B23 -> 20.469144 | D23: =C23*Assumptions!B6 -> 532.19774 | E23: Higher delay raises working-capital drag
A24: 45 | B24: =Assumptions!B5*Assumptions!B18*A24/365 -> 384.65753 | C24: =Assumptions!B22-Assumptions!B39-Assumptions!B40-B24 -> -107.75003 | D24: =C24*Assumptions!B6 -> -2801.5009 | E24: Higher delay raises working-capital drag
A25: 60 | B25: =Assumptions!B5*Assumptions!B18*A25/365 -> 512.87671 | C25: =Assumptions!B22-Assumptions!B39-Assumptions!B40-B25 -> -235.96921 | D25: =C25*Assumptions!B6 -> -6135.1995 | E25: Higher delay raises working-capital drag
A26: 75 | B26: =Assumptions!B5*Assumptions!B18*A26/365 -> 641.09589 | C26: =Assumptions!B22-Assumptions!B39-Assumptions!B40-B26 -> -364.18839 | D26: =C26*Assumptions!B6 -> -9468.8982 | E26: Higher delay raises working-capital drag
A27: 90 | B27: =Assumptions!B5*Assumptions!B18*A27/365 -> 769.31507 | C27: =Assumptions!B22-Assumptions!B39-Assumptions!B40-B27 -> -492.40757 | D27: =C27*Assumptions!B6 -> -12802.597 | E27: Higher delay raises working-capital drag
A30: Procedure revenue sensitivity
A31: Procedure rev / dose | B31: Net op margin / dose | C31: Annualized at 26 doses | D31: Comment
A32: 500 | B32: =A32-Assumptions!B39-Assumptions!B40-Assumptions!B41 -> -357.75003 | C32: =B32*Assumptions!B6 -> -9301.5009 | D32: Higher revenue can offset fixed friction
A33: 650 | B33: =A33-Assumptions!B39-Assumptions!B40-Assumptions!B41 -> -207.75003 | C33: =B33*Assumptions!B6 -> -5401.5009 | D33: Higher revenue can offset fixed friction
A34: 750 | B34: =A34-Assumptions!B39-Assumptions!B40-Assumptions!B41 -> -107.75003 | C34: =B34*Assumptions!B6 -> -2801.5009 | D34: Higher revenue can offset fixed friction
A35: 850 | B35: =A35-Assumptions!B39-Assumptions!B40-Assumptions!B41 -> -7.7500342 | C35: =B35*Assumptions!B6 -> -201.50089 | D35: Higher revenue can offset fixed friction
A36: 1000 | B36: =A36-Assumptions!B39-Assumptions!B40-Assumptions!B41 -> 142.24997 | C36: =B36*Assumptions!B6 -> 3698.4991 | D36: Higher revenue can offset fixed friction
A37: 1200 | B37: =A37-Assumptions!B39-Assumptions!B40-Assumptions!B41 -> 342.24997 | C37: =B37*Assumptions!B6 -> 8898.4991 | D37: Higher revenue can offset fixed friction

Sheet Sources
A1: Source Index
A2: Plain-text URLs used to ground the model assumptions.
A3: Official and cited sources
A5: Topic | B5: URL | C5: Used for
A6: CMS Part B drug payment limits overview | B6: https://www.cms.gov/files/document/part-b-drug-payment-limits-overview.pdf-0 | C6: Medicare benchmark context
A7: CMS HCPCS Level II coding procedures | B7: https://www.cms.gov/medicare/coding-billing/healthcare-common-procedure-system/level-ii-coding-process | C7: HCPCS and coding logic
A8: CMS pass-through payment status and NTAP APC assignment | B8: https://www.cms.gov/medicare/payment/prospective-payment-systems/hospital-outpatient/pass-through-payment-status-new-technology-ambulatory-payment-classification-apc | C8: OPPS pass-through timing
A9: CMS OPPS overview and payment policy guide | B9: https://www.cms.gov/cms-guide-medical-technology-companies-and-other-interested-parties/payment/opps | C9: Hospital outpatient payment mechanics
A10: CMS pass-through submission requirements | B10: https://www.cms.gov/files/document/determine-eligibility-drugs-biologicals-transitional-pass-through-payment-under-hospital-outpatient.pdf | C10: Pass-through submission requirements
A11: HRSA 340B ceiling price FAQ | B11: https://www.hrsa.gov/about/faqs/how-340b-ceiling-price-calculated | C11: 340B pricing rules
A12: HRSA new drug price estimation | B12: https://340bpricingsubmissions.hrsa.gov/Help/Manufacturer/Pricing%20Formulas/New%20Drug%20Price%20Estimation.htm | C12: New-drug 340B estimate
A13: HRSA duplicate discount prohibition | B13: https://www.hrsa.gov/opa/program-requirements/medicaid-exclusion | C13: Medicaid carve-in / carve-out rules
A14: Medicaid.gov Physician Administered Drugs | B14: https://www.medicaid.gov/medicaid/prescription-drugs/state-prescription-drug-resources/physician-administered-drugs-pad | C14: PAD billing logic
A15: Medicaid.gov EPSDT | B15: https://www.medicaid.gov/medicaid/benefits/early-and-periodic-screening-diagnostic-and-treatment | C15: EPSDT coverage logic
A16: Colorado Medicaid state plan | B16: https://hcpf.colorado.gov/sites/hcpf/files/4_19_B-Methods%20and%20Standards%20for%20Establishing%20Payment%20Rates-Other%20Types%20of%20Care.pdf | C16: State reimbursement example
... A23: UnitedHealthcare Aqneursa PA policy | B23: https://www.uhcprovider.com/content/dam/provider/docs/public/prior-auth/drugs-pharmacy/commercial/a-g/PA-Med-Nec-Aqneursa.pdf | C23: Commercial managed access example
