Workbook

Sheet Instructions
A1: Adrabetadex Final ARM Provider Net Cost Recovery Tool
A2: Reimbursement-readiness and economic-exposure model for ARM-led provider conversations after approved authorization.
A4: Required field-use framing | B4: This model assumes payer authorization has been approved for the patient, dose, frequency, site of care, and sourcing pathway reflected in the selected scenario. If authorization is pending, denied, under appeal, expired, or inconsistent with the modeled site/sourcing pathway, the economic output should not be used.
A8: Standard caveat | B8: This scenario is for reimbursement planning only. It does not guarantee coverage, coding, payment, reimbursement, acquisition cost, provider margin, payer behavior, 340B pricing, pass-through status, HCPCS assignment, or claim outcome. Providers are responsible for verifying coding, billing, payer rules, contract terms, documentation, and institutional policy before claim submission.
A13: Positioning
A14: Use as | B14: A reimbursement-readiness and economic-exposure model for approved-scope scenarios.
A15: Do not use as | B15: A provider profitability calculator, coding recommendation, coverage guarantee, payment guarantee, manufacturer funding calculator, 340B spread calculator, or replacement for provider review.
A16: Release gate | B16: Economics calculate only when PA is approved and the approval scope matches dose, frequency, site of care, sourcing pathway, authorization dates, and authorized dose count.
A17: Scenario control | B17: One selected scenario ID drives all categorical and numeric assumptions. Manual overrides are blank by default and visible when activated.
A21: Audience layers
A23: Component | B23: Audience | C23: Requirement
A24: Locked ARM calculator | B24: ARMs and internal reimbursement team | C24: Controlled scenario model with locked formulas, approved input cells, and visible risk flags.
A25: ARM conversation guide | B25: ARMs | C25: Stepwise workflow for provider conversations.
A26: Provider-facing worksheet/PDF | B26: Provider finance, pharmacy, billing, access teams | C26: Educational summary using provider-entered assumptions. No guarantee language.
A27: Billing-readiness checklist | B27: Provider billing/revenue cycle | C27: Candidate claim-readiness prompts only; does not prescribe codes.
A28: Policy/source register | B28: MLR, compliance, market access | C28: CMS, Medicaid, HRSA, payer-policy, and planning assumptions with source dates and owners.

Sheet Scenario Engine
A1: Scenario Engine
A2: Single scenario ID drives categorical and numeric assumptions.
A4: Selected Scenario ID | B4: S01
A5: Scenario name | B5: =INDEX($B$35:$B$42,MATCH($B$4,$A$35:$A$42,0)) -> 340B COE/HOPD, buy-and-bill, pass-through-if-granted
A6: Manual override active? | B6: No
A8: Field-use framing | B8: This model assumes payer authorization has been approved for the patient, dose, frequency, site of care, and sourcing pathway reflected in the selected scenario. If authorization is pending, denied, under appeal, expired, or inconsistent with the modeled site/sourcing pathway, the economic output should not be used.
A10: Scenario Field | B10: Preset Value | C10: Manual Override | D10: Active Value | E10: Active Source | F10: Notes
A11: Site of care | B11: =INDEX($D$35:$S$42,MATCH($B$4,$A$35:$A$42,0),1) -> HOPD | D11: =IF($B$6="Yes",IF(C11<>"",C11,B11),B11) -> HOPD | E11: =IF($B$6="Yes",IF(C11<>"","Manual Override","Preset (override on, blank override)"),"Preset") -> Preset | F11: HOPD, physician office, ASC/other, inpatient exception
A12: Site profile | B12: =INDEX($D$35:$S$42,MATCH($B$4,$A$35:$A$42,0),2) -> COE | D12: =IF($B$6="Yes",IF(C12<>"",C12,B12),B12) -> COE | E12: =IF($B$6="Yes",IF(C12<>"","Manual Override","Preset (override on, blank override)"),"Preset") -> Preset | F12: COE, pediatric specialty hospital, academic center, community site
A13: 340B status | B13: =INDEX($D$35:$S$42,MATCH($B$4,$A$35:$A$42,0),3) -> Yes | D13: =IF($B$6="Yes",IF(C13<>"",C13,B13),B13) -> Yes | E13: =IF($B$6="Yes",IF(C13<>"","Manual Override","Preset (override on, blank override)"),"Preset") -> Preset | F13: Yes, no, unknown, not applicable
A14: Payer type | B14: =INDEX($D$35:$S$42,MATCH($B$4,$A$35:$A$42,0),4) -> Medicare | D14: =IF($B$6="Yes",IF(C14<>"",C14,B14),B14) -> Medicare | E14: =IF($B$6="Yes",IF(C14<>"","Manual Override","Preset (override on, blank override)"),"Preset") -> Preset | F14: Commercial, Medicaid FFS, Medicaid MCO, Medicare, other
A15: Sourcing pathway | B15: =INDEX($D$35:$S$42,MATCH($B$4,$A$35:$A$42,0),5) -> Buy-and-bill | D15: =IF($B$6="Yes",IF(C15<>"",C15,B15),B15) -> Buy-and-bill | E15: =IF($B$6="Yes",IF(C15<>"","Manual Override","Preset (override on, blank override)"),"Preset") -> Preset | F15: Buy-and-bill, white-bagging, specialty pharmacy, mixed
A16: Product coding status | B16: =INDEX($D$35:$S$42,MATCH($B$4,$A$35:$A$42,0),6) -> C9399/NOC | D16: =IF($B$6="Yes",IF(C16<>"",C16,B16),B16) -> C9399/NOC | E16: =IF($B$6="Yes",IF(C16<>"","Manual Override","Preset (override on, blank override)"),"Preset") -> Preset | F16: Separates HCPCS/NOC/payer-directed coding from payment state
A17: Payment status | B17: =INDEX($D$35:$S$42,MATCH($B$4,$A$35:$A$42,0),7) -> OPPS pass-through active | D17: =IF($B$6="Yes",IF(C17<>"",C17,B17),B17) -> OPPS pass-through active | E17: =IF($B$6="Yes",IF(C17<>"","Manual Override","Preset (override on, blank override)"),"Preset") -> Preset | F17: Payment branch, not coding status
A18: Authorization type | B18: =INDEX($D$35:$S$42,MATCH($B$4,$A$35:$A$42,0),8) -> Initial approval | D18: =IF($B$6="Yes",IF(C18<>"",C18,B18),B18) -> Initial approval | E18: =IF($B$6="Yes",IF(C18<>"","Manual Override","Preset (override on, blank override)"),"Preset") -> Preset | F18: Initial approval or reauthorization approval
A19: Modeled dose | B19: =INDEX($D$35:$S$42,MATCH($B$4,$A$35:$A$42,0),9) -> 900 | D19: =IF($B$6="Yes",IF(C19<>"",C19,B19),B19) -> 900 | E19: =IF($B$6="Yes",IF(C19<>"","Manual Override","Preset (override on, blank override)"),"Preset") -> Preset | F19: Must match authorized dose
A20: Modeled frequency | B20: =INDEX($D$35:$S$42,MATCH($B$4,$A$35:$A$42,0),10) -> Every 2 weeks | D20: =IF($B$6="Yes",IF(C20<>"",C20,B20),B20) -> Every 2 weeks | E20: =IF($B$6="Yes",IF(C20<>"","Manual Override","Preset (override on, blank override)"),"Preset") -> Preset | F20: Must match authorized frequency
A21: Administrations per year | B21: =INDEX($D$35:$S$42,MATCH($B$4,$A$35:$A$42,0),11) -> 26 | D21: =IF($B$6="Yes",IF(C21<>"",C21,B21),B21) -> 26 | E21: =IF($B$6="Yes",IF(C21<>"","Manual Override","Preset (override on, blank override)"),"Preset") -> Preset | F21: Default 26 for every two weeks
A22: Acquisition basis | B22: =INDEX($D$35:$S$42,MATCH($B$4,$A$35:$A$42,0),12) -> 340B | D22: =IF($B$6="Yes",IF(C22<>"",C22,B22),B22) -> 340B | E22: =IF($B$6="Yes",IF(C22<>"","Manual Override","Preset (override on, blank override)"),"Preset") -> Preset | F22: WAC, 340B, site-entered, payer-directed, specialty pharmacy, other
A23: Payer payment method | B23: =INDEX($D$35:$S$42,MATCH($B$4,$A$35:$A$42,0),13) -> Medicare benchmark | D23: =IF($B$6="Yes",IF(C23<>"",C23,B23),B23) -> Medicare benchmark | E23: =IF($B$6="Yes",IF(C23<>"","Manual Override","Preset (override on, blank override)"),"Preset") -> Preset | F23: Medicare benchmark, commercial contract, Medicaid FFS, Medicaid MCO, manual pricing, payer-specific
A24: Claim type | B24: =INDEX($D$35:$S$42,MATCH($B$4,$A$35:$A$42,0),14) -> UB-04/837I | D24: =IF($B$6="Yes",IF(C24<>"",C24,B24),B24) -> UB-04/837I | E24: =IF($B$6="Yes",IF(C24<>"","Manual Override","Preset (override on, blank override)"),"Preset") -> Preset | F24: UB-04/837I or CMS-1500/837P based on site
A25: Medicaid line of business | B25: =INDEX($D$35:$S$42,MATCH($B$4,$A$35:$A$42,0),15) -> Not applicable | D25: =IF($B$6="Yes",IF(C25<>"",C25,B25),B25) -> Not applicable | E25: =IF($B$6="Yes",IF(C25<>"","Manual Override","Preset (override on, blank override)"),"Preset") -> Preset | F25: FFS, MCO, not applicable
A26: 340B treatment | B26: =INDEX($D$35:$S$42,MATCH($B$4,$A$35:$A$42,0),16) -> Carve-out | D26: =IF($B$6="Yes",IF(C26<>"",C26,B26),B26) -> Carve-out | E26: =IF($B$6="Yes",IF(C26<>"","Manual Override","Preset (override on, blank override)"),"Preset") -> Preset | F26: Carve-in, carve-out, unresolved, unknown, not applicable
A34: Scenario ID | B34: Scenario Name | C34: Purpose | D34: Site of care | E34: Site profile | F34: 340B status | G34: Payer type | H34: Sourcing pathway | I34: Product coding status | J34: Payment status | K34: Authorization type | L34: Modeled dose | M34: Modeled frequency | N34: Administrations per year | O34: Acquisition basis | P34: Payer payment method | Q34: Claim type | R34: Medicaid LOB | S34: 340B treatment | T34: Allowed drug reimbursement | U34: Acquisition cost | V34: Procedure/admin revenue | W34: Other services | X34: Pharmacy handling | Y34: Labor/admin | Z34: Billing/revenue-cycle | AA34: Claim denial rate | AB34: Appeal recovery rate | AC34: Days to payment | AD34: Financing rate | AE34: WAC per vial | AF34: Vial size mg | AG34: Scenario note
A35: S01 | B35: 340B COE/HOPD, buy-and-bill, pass-through-if-granted | C35: Core launch planning scenario. | D35: HOPD | E35: COE | F35: Yes | G35: Medicare | H35: Buy-and-bill | I35: C9399/NOC | J35: OPPS pass-through active | K35: Initial approval | L35: 900 | M35: Every 2 weeks | N35: 26 | O35: 340B | P35: Medicare benchmark | Q35: UB-04/837I | R35: Not applicable | S35: Carve-out | T35: 40170 | U35: 29991 | V35: 500 | W35: 0 | X35: 400 | Y35: 750 | Z35: 300 | AA35: 0.075 | AB35: 0.6 | AC35: 75 | AD35: 0.08 | AE35: 39000 | AF35: 900 | AG35: Pass-through used only if granted and effective; otherwise re-run S02.
A36: S02 | B36: 340B COE/HOPD, pre-pass-through/interim coding | C36: Launch bridge risk scenario. | D36: HOPD | E36: COE | F36: Yes | G36: Medicare | H36: Buy-and-bill | I36: C9399/NOC | J36: Manual pricing | K36: Initial approval | L36: 900 | M36: Every 2 weeks | N36: 26 | O36: 340B | P36: Manual pricing | Q36: UB-04/837I | R36: Not applicable | S36: Carve-out | T36: 37050 | U36: 29991 | V36: 500 | W36: 0 | X36: 500 | Y36: 850 | Z36: 400 | AA36: 0.12 | AB36: 0.5 | AC36: 95 | AD36: 0.08 | AE36: 39000 | AF36: 900 | AG36: Manual-review branch; documentation and payer confirmation drive risk.
A37: S03 | B37: 340B COE/HOPD, product-specific HCPCS active | C37: Post-bridge steady-state scenario. | D37: HOPD | E37: COE | F37: Yes | G37: Medicare | H37: Buy-and-bill | I37: Product-specific HCPCS assigned | J37: ASP available | K37: Reauthorization approval | L37: 900 | M37: Every 2 weeks | N37: 26 | O37: 340B | P37: Medicare benchmark | Q37: UB-04/837I | R37: Not applicable | S37: Carve-out | T37: 39273 | U37: 29991 | V37: 500 | W37: 0 | X37: 350 | Y37: 650 | Z37: 275 | AA37: 0.05 | AB37: 0.7 | AC37: 65 | AD37: 0.08 | AE37: 39000 | AF37: 900 | AG37: Payment method still depends on setting, payer, and effective files.
A38: S04 | B38: Non-340B HOPD, commercial buy-and-bill | C38: Sensitivity scenario for thinner economics. | D38: HOPD | E38: Academic center | F38: No | G38: Commercial | H38: Buy-and-bill | I38: Payer-directed code | J38: Commercial contracted | K38: Initial approval | L38: 900 | M38: Every 2 weeks | N38: 26 | O38: WAC | P38: Commercial contract | Q38: UB-04/837I | R38: Not applicable | S38: Not applicable | T38: 42000 | U38: 39000 | V38: 625 | W38: 0 | X38: 450 | Y38: 700 | Z38: 350 | AA38: 0.09 | AB38: 0.55 | AC38: 80 | AD38: 0.08 | AE38: 39000 | AF38: 900 | AG38: Use payer contract or site-entered allowed amount; do not default to Medicare.
A39: S05 | B39: White-bagging/specialty pharmacy sourcing | C39: Inventory-risk reduction but limited/no drug spread. | D39: HOPD | E39: COE | F39: Unknown | G39: Commercial | H39: White-bagging | I39: Payer-directed code | J39: White-bagged/no drug reimbursement | K39: Initial approval | L39: 900 | M39: Every 2 weeks | N39: 26 | O39: Specialty pharmacy | P39: Payer-specific | Q39: UB-04/837I | R39: Not applicable | S39: Not applicable | T39: 0 | U39: 0 | V39: 450 | W39: 0 | X39: 250 | Y39: 600 | Z39: 275 | AA39: 0.06 | AB39: 0.5 | AC39: 55 | AD39: 0.08 | AE39: 39000 | AF39: 900 | AG39: Drug reimbursement and acquisition exposure are zero unless payer terms say otherwise.
A40: S06 | B40: Medicaid FFS 340B | C40: NDC/PAD, carve-in/carve-out, and duplicate-discount branch. | D40: HOPD | E40: Pediatric specialty hospital | F40: Yes | G40: Medicaid FFS | H40: Buy-and-bill | I40: Payer-directed code | J40: Medicaid FFS state-specific | K40: Initial approval | L40: 900 | M40: Every 2 weeks | N40: 26 | O40: 340B | P40: Medicaid FFS | Q40: UB-04/837I | R40: FFS | S40: Unresolved | T40: 36000 | U40: 29991 | V40: 475 | W40: 0 | X40: 500 | Y40: 800 | Z40: 450 | AA40: 0.1 | AB40: 0.5 | AC40: 90 | AD40: 0.08 | AE40: 39000 | AF40: 900 | AG40: Requires state-specific methodology, NDC/PAD fields, and duplicate-discount resolution.
A41: S07 | B41: Medicaid MCO | C41: Plan-specific Medicaid branch. Do not assume FFS logic. | D41: HOPD | E41: Community site | F41: Unknown | G41: Medicaid MCO | H41: Mixed | I41: Payer-directed code | J41: Medicaid MCO plan-specific | K41: Initial approval | L41: 900 | M41: Every 2 weeks | N41: 26 | O41: Payer-directed | P41: Medicaid MCO | Q41: UB-04/837I | R41: MCO | S41: Unknown | T41: 35000 | U41: 39000 | V41: 475 | W41: 0 | X41: 500 | Y41: 850 | Z41: 500 | AA41: 0.11 | AB41: 0.45 | AC41: 95 | AD41: 0.08 | AE41: 39000 | AF41: 900 | AG41: Requires plan-specific confirmation; FFS payment logic is not assumed.
A42: S08 | B42: Physician office pre-ASP | C42: 103% WAC benchmark sensitivity only. | D42: Physician office | E42: Community site | F42: No | G42: Medicare | H42: Buy-and-bill | I42: No product-specific HCPCS | J42: Pre-ASP WAC benchmark | K42: Initial approval | L42: 900 | M42: Every 2 weeks | N42: 26 | O42: WAC | P42: Medicare benchmark | Q42: CMS-1500/837P | R42: Not applicable | S42: Not applicable | T42: 40170 | U42: 39000 | V42: 325 | W42: 0 | X42: 250 | Y42: 400 | Z42: 250 | AA42: 0.07 | AB42: 0.6 | AC42: 60 | AD42: 0.08 | AE42: 39000 | AF42: 900 | AG42: 103% WAC is used only for physician office pre-ASP sensitivity.

Sheet Product Economics
A1: Product Economics
A2: Gross exposure, acquisition, reimbursement, and dosing formulas.
A3: Field | B3: Value | C3: Source | D3: Notes
A4: WAC per vial | B4: =INDEX('Scenario Engine'!$AE$35:$AE$42,MATCH('Scenario Engine'!$B$4,'Scenario Engine'!$A$35:$A$42,0)) -> 39000 | C4: Scenario library | D4: Internal planning assumption; update through source register.
A5: Vial size (mg) | B5: =INDEX('Scenario Engine'!$AF$35:$AF$42,MATCH('Scenario Engine'!$B$4,'Scenario Engine'!$A$35:$A$42,0)) -> 900 | C5: Scenario library | D5: Must align with dosing and wastage logic.
A6: Dose per administration (mg) | B6: ='Scenario Engine'!$D$19 -> 900 | C6: Scenario engine | D6: Must match authorized dose.
A7: Dosing frequency | B7: ='Scenario Engine'!$D$20 -> Every 2 weeks | C7: Scenario engine | D7: Must match authorized frequency.
A8: Administrations per year | B8: ='Scenario Engine'!$D$21 -> 26 | C8: Scenario engine | D8: Default 26 for every two weeks.
A9: Vials per administration | B9: =CEILING(B6/B5,1) -> 1 | C9: Derived | D9: Rounded up to whole vials.
A10: Wastage amount (mg) | B10: =(B9*B5)-B6 -> 0 | C10: Derived | D10: JW/JZ handling is a checklist/risk prompt only.
A11: Gross Drug Exposure per Dose | B11: =B4*B9 -> 39000 | C11: Derived | D11: WAC per vial x vials per administration.
A12: Acquisition basis | B12: ='Scenario Engine'!$D$22 -> 340B | C12: Scenario engine | D12: WAC, 340B, site-entered, payer-directed, specialty pharmacy, or other.
A13: Scenario acquisition cost default | B13: =INDEX('Scenario Engine'!$U$35:$U$42,MATCH('Scenario Engine'!$B$4,'Scenario Engine'!$A$35:$A$42,0)) -> 29991 | C13: Scenario library | D13: Blank manual overrides remain blank until actively enabled.
A14: Acquisition Cost per Dose | B14: =IF(OR(B12="Specialty pharmacy",B12="White-bagging"),0,B13) -> 29991 | C14: Derived | D14: Zero for white-bagging/SP unless payer-specific terms say otherwise.
A15: Payer payment method | B15: ='Scenario Engine'!$D$23 -> Medicare benchmark | C15: Scenario engine | D15: Payment branch, not coding status.
A16: Allowed Drug Reimbursement per Dose | B16: =IF(OR('Scenario Engine'!$D$15="White-bagging",'Scenario Engine'!$D$15="Specialty pharmacy"),0,IF(AND('Scenario Engine'!$D$11="Physician office",'Scenario Engine'!$D$17="Pre-ASP WAC benchmark"),B11*1.03,INDEX('Scenario Engine'!$T$35:$T$42,MATCH('Scenario Engine'!$B$4,'Scenario Engine'!$A$35:$A$42,0)))) -> 40170 | C16: Derived | D16: 103% WAC branch applies only to physician office pre-ASP.
A17: Procedure/Admin Revenue | B17: =INDEX('Scenario Engine'!$V$35:$V$42,MATCH('Scenario Engine'!$B$4,'Scenario Engine'!$A$35:$A$42,0)) -> 500 | C17: Scenario library | D17: Provider/site-entered benchmark or planning default.
A18: Other Reimbursable Services | B18: =INDEX('Scenario Engine'!$W$35:$W$42,MATCH('Scenario Engine'!$B$4,'Scenario Engine'!$A$35:$A$42,0)) -> 0 | C18: Scenario library | D18: Optional.
A19: Gross Recovery per Dose | B19: =B16+B17+B18 -> 40670 | C19: Derived | D19: Drug reimbursement plus administration revenue.

Sheet Coding Payment
A1: Coding and Payment State
A2: Coding status and payment status remain distinct throughout the tool.
A3: Field | B3: Active Value | C3: Interpretation | D3: Guardrail
A4: Product coding status | B4: ='Scenario Engine'!$D$16 -> C9399/NOC | C4: How product may be reported on a claim. | D4: No product-specific HCPCS; C9399/NOC; product-specific HCPCS assigned; payer-directed code.
A5: Payment status | B5: ='Scenario Engine'!$D$17 -> OPPS pass-through active | C5: How reimbursement may be calculated or adjudicated. | D5: Pre-ASP WAC benchmark; OPPS pass-through active; ASP available; OPPS non-pass-through; manual pricing; commercial contracted; Medicaid-specific; white-bagged/no drug reimbursement.
A6: Hard rule | B6: Pass-through active is not coding status. | C6: Pass-through is a payment state, not a product coding state. | D6: Do not conflate C-codes/HCPCS/NOC with pass-through/payment methodology.
A7: Medicare branch | B7: =IF(AND('Scenario Engine'!$D$11="Physician office",'Scenario Engine'!$D$17="Pre-ASP WAC benchmark"),"Physician office pre-ASP WAC x 103% only",IF('Scenario Engine'!$D$17="ASP available","ASP branch",IF('Scenario Engine'!$D$17="OPPS pass-through active","OPPS pass-through branch if granted/effective",'Scenario Engine'!$D$17))) -> OPPS pass-through branch if granted/effective | C7: Branch logic | D7: 103% WAC is not applied universally.
A8: Commercial branch | B8: =IF('Scenario Engine'!$D$14="Commercial","Contract/manual pricing; do not default to Medicare","Not commercial") -> Not commercial | C8: Branch logic | D8: Use payer-specific allowed amount or provider-entered contract terms.
A9: Medicaid branch | B9: =IF(OR('Scenario Engine'!$D$14="Medicaid FFS",'Scenario Engine'!$D$14="Medicaid MCO"),'Scenario Engine'!$D$14&" - state/plan-specific with PAD/NDC checks","Not Medicaid") -> Not Medicaid | C9: Branch logic | D9: MCO does not assume FFS logic.

Sheet Site Channel
A1: Site and Channel
A2: Site, payer, 340B, Medicaid, and sourcing branches.
A3: Field | B3: Active Value | C3: Source | D3: Notes
A4: Site of care | B4: ='Scenario Engine'!$D$11 -> HOPD | C4: Scenario driver | D4: Must match authorized site of care.
A5: Site profile | B5: ='Scenario Engine'!$D$12 -> COE | C5: Scenario driver | D5: COE, pediatric specialty hospital, academic center, community site.
A6: 340B status | B6: ='Scenario Engine'!$D$13 -> Yes | C6: Scenario driver | D6: Eligibility must be site and billing-entity specific.
A7: Payer type | B7: ='Scenario Engine'!$D$14 -> Medicare | C7: Scenario driver | D7: Commercial, Medicaid FFS, Medicaid MCO, Medicare, or other.
A8: Sourcing pathway | B8: ='Scenario Engine'!$D$15 -> Buy-and-bill | C8: Scenario driver | D8: Must match authorized sourcing pathway.
A9: White-bagging rule | B9: =IF(OR(B8="White-bagging",B8="Specialty pharmacy"),"Drug reimbursement/spread set to zero unless payer-specific value is entered","Buy-and-bill or mixed pathway") -> Buy-and-bill or mixed pathway | C9: Derived | D9: White-bagging reduces inventory exposure but limits/no drug spread.
A10: 340B caveat | B10: 340B acquisition values are illustrative unless site-verified. This model does not guarantee 340B eligibility, 340B ceiling price, sub-ceiling price, provider acquisition cost, payer-recognized payment basis, or payer reimbursement outcome. | C10: Required caveat | D10: Display when a 340B acquisition assumption is used.

Sheet Operating Burden
A1: Operating Burden
A2: Claim-friction, staffing, billing, and timing burden.
A3: Field | B3: Value | C3: Source | D3: Notes
A4: Pharmacy handling cost | B4: =INDEX('Scenario Engine'!$X$35:$X$42,MATCH('Scenario Engine'!$B$4,'Scenario Engine'!$A$35:$A$42,0)) -> 400 | C4: Scenario library | D4: Per administration.
A5: Labor/admin cost | B5: =INDEX('Scenario Engine'!$Y$35:$Y$42,MATCH('Scenario Engine'!$B$4,'Scenario Engine'!$A$35:$A$42,0)) -> 750 | C5: Scenario library | D5: Per administration.
A6: Billing/revenue-cycle cost | B6: =INDEX('Scenario Engine'!$Z$35:$Z$42,MATCH('Scenario Engine'!$B$4,'Scenario Engine'!$A$35:$A$42,0)) -> 300 | C6: Scenario library | D6: Per administration.
A7: Operating Burden per Dose | B7: =SUM(B4:B6) -> 1450 | C7: Derived | D7: Pharmacy handling + labor/admin + billing/revenue-cycle cost.
A8: Claim denial rate | B8: =INDEX('Scenario Engine'!$AA$35:$AA$42,MATCH('Scenario Engine'!$B$4,'Scenario Engine'!$A$35:$A$42,0)) -> 0.075 | C8: Scenario library | D8: Post-service claim denial, not PA denial.
A9: Appeal recovery rate | B9: =INDEX('Scenario Engine'!$AB$35:$AB$42,MATCH('Scenario Engine'!$B$4,'Scenario Engine'!$A$35:$A$42,0)) -> 0.6 | C9: Scenario library | D9: Claim appeal recovery only.
A10: Days to payment | B10: =INDEX('Scenario Engine'!$AC$35:$AC$42,MATCH('Scenario Engine'!$B$4,'Scenario Engine'!$A$35:$A$42,0)) -> 75 | C10: Scenario library | D10: Cash-flow timing burden.
A11: Financing rate | B11: =INDEX('Scenario Engine'!$AD$35:$AD$42,MATCH('Scenario Engine'!$B$4,'Scenario Engine'!$A$35:$A$42,0)) -> 0.08 | C11: Scenario library | D11: Used only for financing drag.
A12: Expected Claim Denial Drag | B12: ='Product Economics'!B19*B8*(1-B9) -> 1220.1 | C12: Derived | D12: Gross recovery x claim denial rate x unrecovered share.
A13: Financing Drag | B13: ='Product Economics'!B14*B11*(B10/365) -> 493.00274 | C13: Derived | D13: Acquisition cost x financing rate x days to payment / 365.

Sheet Payer Controls
A1: Payer Controls and Authorization Gate
A2: PA approval and scope match are hard prerequisites before economics calculate.
A3: Input / Check | B3: Value | C3: Required | D3: Notes
A4: PA status | B4: Approved | C4: Yes | D4: Not started, Submitted/pending, Denied/appeal, Approved, Reauthorization approved, Reauthorization pending.
A5: Approval type | B5: Initial approval | C5: Yes | D5: Initial approval or reauthorization approval.
A6: Approval start date | B6: 46143 | C6: Yes | D6: Used to calculate authorized treatment window.
A7: Approval end date | B7: 46387 | C7: Yes | D7: Must not be expired.
A8: Authorized number of doses | B8: 26 | C8: Yes | D8: Limits annualized economics when authorization is partial-year.
A9: Authorized dose | B9: 900 | C9: Yes | D9: Must equal modeled dose.
A10: Authorized frequency | B10: Every 2 weeks | C10: Yes | D10: Must equal modeled frequency.
A11: Authorized site of care | B11: HOPD | C11: Yes | D11: Must equal modeled site of care.
A12: Authorized sourcing pathway | B12: Buy-and-bill | C12: Yes | D12: Must equal modeled sourcing pathway.
A13: Approval reference number | B13: Provider-entered | C13: No | D13: Useful for documentation but not required for calculation.
A14: Payer SOC confirmed | B14: Yes | C14: Yes | D14: Flags site-of-care restriction risk if not confirmed.
A15: Payer sourcing restriction confirmed | B15: Yes | C15: Yes | D15: Flags white-bagging/specialty pharmacy risk if not confirmed.
A16: Specialist requirement confirmed | B16: Yes | C16: Yes | D16: Documentation risk if not confirmed.
A17: Baseline documentation confirmed | B17: Yes | C17: Yes | D17: Initial approval/reauthorization risk if not confirmed.
A18: Continuation endpoint defined | B18: Yes | C18: Yes | D18: Reauthorization risk if not defined.
A19: NDC | C19: Yes for Medicaid | D19: Required for Medicaid PAD logic where applicable.
A20: 11-digit NDC format confirmed | B20: Not applicable | C20: Yes for Medicaid | D20: Provider validation checkbox.
A21: Unit of measure | C21: Yes for Medicaid | D21: Must align with claim requirements.
A22: Quantity administered | C22: Yes for Medicaid | D22: Required for claim integrity.
A23: Claim type | B23: UB-04/837I | C23: Yes | D23: UB-04/837I or CMS-1500/837P based on site.
A24: 340B carve-in/carve-out | B24: Carve-out | C24: If 340B + Medicaid | D24: Required for duplicate-discount risk assessment.
A25: Medicaid Exclusion File status | B25: Provider validation required | C25: Prompt | D25: Provider validation required where relevant.
A26: MCO plan-specific policy confirmed | B26: Not applicable | C26: Yes for Medicaid MCO | D26: Do not assume FFS rules.
A27: 340B eligibility confirmed | B27: Yes | C27: If 340B used | D27: Must be site and billing-entity specific.
A28: 340B applies to service location | B28: Yes | C28: If 340B used | D28: Do not assume entity-level eligibility applies to all services.
A29: 340B acquisition assumption type | B29: Internal planning assumption | C29: If 340B used | D29: Site-verified, internal planning assumption, or unknown.
A30: Medicaid duplicate-discount risk resolved | B30: Not applicable | C30: If Medicaid + 340B | D30: If unresolved, output is Not modellable.
A31: JW/JZ wastage handling confirmed | B31: No - provider validation required | C31: Prompt | D31: Claim-documentation risk only; does not prescribe billing.
A34: PA gate message | B34: =IF(B4="Not started","PA not initiated - economics not actionable.",IF(B4="Submitted/pending","PA pending - reimbursement scenario not yet executable.",IF(B4="Denied/appeal","PA unresolved - economic result not reliable.",IF(B4="Reauthorization pending","Reauthorization pending - do not calculate beyond current authorization window.","PA approved status present.")))) -> PA approved status present.
A35: PA approved for calculation? | B35: =OR(B4="Approved",B4="Reauthorization approved") -> TRUE
A36: Approval scope match? | B36: =AND(B35,B9='Scenario Engine'!$D$19,B10='Scenario Engine'!$D$20,B11='Scenario Engine'!$D$11,B12='Scenario Engine'!$D$15,B7>=TODAY(),B8>0) -> TRUE
A37: Scope warning | B37: =IF(B36,"", "Authorization exists, but approval scope does not match the selected reimbursement scenario. Economic output should not be used until dose, frequency, site of care, sourcing pathway, and authorization period are aligned.")
A38: Medicaid/PAD fields complete? | B38: =IF(OR('Scenario Engine'!$D$14="Medicaid FFS",'Scenario Engine'!$D$14="Medicaid MCO"),AND(B19<>"",B20="Yes",B21<>"",B22<>"",B23<>"",IF('Scenario Engine'!$D$14="Medicaid MCO",B26="Yes",TRUE())),TRUE()) -> TRUE
A39: 340B duplicate-discount resolved? | B39: =IF(AND(OR('Scenario Engine'!$D$14="Medicaid FFS",'Scenario Engine'!$D$14="Medicaid MCO"),'Scenario Engine'!$D$13="Yes"),B30="Yes",TRUE()) -> TRUE
A40: Readiness status | B40: =IF(NOT(B35),B34,IF(NOT(B36),"Not modellable - approval scope mismatch",IF(NOT(B38),"Not modellable - Medicaid/PAD fields unresolved",IF(NOT(B39),"Not modellable - 340B Medicaid duplicate-discount unresolved","Approved scope matches modeled scenario - economics calculated")))) -> Approved scope matches modeled scenario - economics calculated
A41: Modellable? | B41: =AND(B35,B36,B38,B39) -> TRUE
A42: Authorization window label | B42: =IF(AND(B41,B8<'Product Economics'!B8),"Projected only through currently authorized treatment window.","")

Sheet Calculator
A1: Calculator
A2: Transparent formulas and audit trail.
A3: Metric | B3: Value | C3: Formula / Source | D3: Notes
A4: Readiness status | B4: ='Payer Controls'!$B$40 -> Approved scope matches modeled scenario - economics calculated | C4: Authorization gate | D4: Economics suppress unless modellable.
A5: Modellable? | B5: ='Payer Controls'!$B$41 -> TRUE | C5: Authorization gate | D5: TRUE only after PA approval, scope match, Medicaid/PAD, and duplicate-discount checks pass.
A6: Gross Drug Exposure per Dose | B6: =IF($B$5,'Product Economics'!B11,"") -> 39000 | C6: WAC x vials | D6: Formula required by spec.
A7: Acquisition Cost per Dose | B7: =IF($B$5,'Product Economics'!B14,"") -> 29991 | C7: Scenario-specific acquisition basis | D7: Zero if white-bagging/SP branch.
A8: Drug Reimbursement per Dose | B8: =IF($B$5,'Product Economics'!B16,"") -> 40170 | C8: Scenario-specific payment method | D8: 103% WAC only in S08 branch.
A9: Administration Revenue per Dose | B9: =IF($B$5,'Product Economics'!B17+'Product Economics'!B18,"") -> 500 | C9: Procedure/Admin + other services | D9: User-entered or approved benchmark.
A10: Gross Recovery per Dose | B10: =IF($B$5,B8+B9,"") -> 40670 | C10: Drug + admin revenue | D10: Formula required by spec.
A11: Operating Burden per Dose | B11: =IF($B$5,'Operating Burden'!B7,"") -> 1450 | C11: Pharmacy + labor + billing cost | D11: Formula required by spec.
A12: Expected Claim Denial Drag | B12: =IF($B$5,'Operating Burden'!B12,"") -> 1220.1 | C12: Gross recovery x claim denial x unrecovered share | D12: Claim denial, not PA denial.
A13: Financing Drag | B13: =IF($B$5,'Operating Burden'!B13,"") -> 493.00274 | C13: Acquisition x financing rate x days/365 | D13: Timing burden.
A14: Net Recovery per Dose | B14: =IF($B$5,B10-B7-B11-B12-B13,"") -> 7515.8973 | C14: Gross recovery less cost and drag | D14: Estimated surplus/shortfall under stated assumptions.
A15: Authorized Administrations | B15: =IF($B$5,MIN('Product Economics'!B8,'Payer Controls'!B8),0) -> 26 | C15: min(admins/year, authorized doses) | D15: Annualized output limited by approved window.
A16: Annual Gross Drug Exposure | B16: =IF($B$5,B6*B15,"") -> 1014000 | C16: Per-dose x authorized administrations
A17: Annual Acquisition Cost | B17: =IF($B$5,B7*B15,"") -> 779766 | C17: Per-dose x authorized administrations
A18: Annual Gross Recovery | B18: =IF($B$5,B10*B15,"") -> 1057420 | C18: Per-dose x authorized administrations
A19: Annual Operating Burden | B19: =IF($B$5,B11*B15,"") -> 37700 | C19: Per-dose x authorized administrations
A20: Annual Claim Denial Drag | B20: =IF($B$5,B12*B15,"") -> 31722.6 | C20: Per-dose x authorized administrations
A21: Annual Financing Drag | B21: =IF($B$5,B13*B15,"") -> 12818.071 | C21: Per-dose x authorized administrations
A22: Annual Net Recovery | B22: =IF($B$5,B14*B15,"") -> 195413.33 | C22: Per-dose x authorized administrations | D22: If partial-year, label projection through approved window.
A23: Projection label | B23: ='Payer Controls'!$B$42 | C23: Authorization window rule | D23: Do not present partial authorization as full-year recovery unless confirmed.

Sheet Output Summary
A1: Adrabetadex Provider Net Cost Recovery Summary
A2: Final ARM v1.0
A4: Scenario summary
A5: Scenario ID | B5: ='Scenario Engine'!$B$4 -> S01 | C5: Scenario name | D5: ='Scenario Engine'!$B$5 -> 340B COE/HOPD, buy-and-bill, pass-through-if-granted
A6: Site | B6: ='Scenario Engine'!$D$11 -> HOPD | C6: Payer | D6: ='Scenario Engine'!$D$14 -> Medicare
A7: 340B | B7: ='Scenario Engine'!$D$13 -> Yes | C7: Sourcing | D7: ='Scenario Engine'!$D$15 -> Buy-and-bill
A8: Coding status | B8: ='Scenario Engine'!$D$16 -> C9399/NOC | C8: Payment status | D8: ='Scenario Engine'!$D$17 -> OPPS pass-through active
A9: PA status | B9: ='Payer Controls'!$B$4 -> Approved | C9: Scope match | D9: =IF('Payer Controls'!$B$36,"Yes","No") -> Yes
A11: Readiness status | B11: ='Payer Controls'!$B$40 -> Approved scope matches modeled scenario - economics calculated
A14: Per-dose economics
A15: WAC exposure | B15: =Calculator!$B$6 -> 39000 | C15: Acquisition cost | D15: =Calculator!$B$7 -> 29991
A16: Allowed drug reimbursement | B16: =Calculator!$B$8 -> 40170 | C16: Admin revenue | D16: =Calculator!$B$9 -> 500
A17: Operating burden | B17: =Calculator!$B$11 -> 1450 | C17: Denial/timing drag | D17: =Calculator!$B$12+Calculator!$B$13 -> 1713.1027
A18: Net recovery | B18: =Calculator!$B$14 -> 7515.8973 | C18: Active override | D18: =IF('Scenario Engine'!$B$6="Yes","Manual override active","No manual override") -> No manual override
A20: Authorized-window economics
A21: Authorized doses | B21: =Calculator!$B$15 -> 26 | C21: Approval dates | D21: ='Payer Controls'!$B$6&" to "&'Payer Controls'!$B$7 -> 46143 to 46387
A22: Net recovery through approved window | B22: =Calculator!$B$22 -> 195413.33 | C22: Projection label | D22: =Calculator!$B$23
A24: Risk flags
A25: Recovery | B25: Cash exposure | C25: Coding/payment | D25: Payer control | E25: Medicaid/PAD | F25: 340B | G25: White-bagging | H25: Site of care
A26: =IF(NOT(Calculator!$B$5),"Not modellable",IF(Calculator!$B$14<0,"High",IF(Calculator!$B$14<2500,"Moderate","Low"))) -> Low | B26: =IF(NOT(Calculator!$B$5),"Not modellable",IF(AND('Product Economics'!$B$14>0,'Operating Burden'!$B$10>=90),"High",IF(AND('Product Economics'!$B$14>0,'Operating Burden'!$B$10>=60),"Moderate","Low"))) -> Moderate | C26: =IF(NOT(Calculator!$B$5),"Not modellable",IF(OR('Scenario Engine'!$D$16="No product-specific HCPCS",'Scenario Engine'!$D$16="C9399/NOC"),"High",IF(OR('Scenario Engine'!$D$17="Manual pricing",'Scenario Engine'!$D$17="Medicaid MCO plan-specific"),"Moderate","Low"))) -> High | D26: =IF(NOT(Calculator!$B$5),"Not modellable",IF('Payer Controls'!$B$14<>"Yes","Moderate","Low")) -> Low | E26: =IF(NOT(Calculator!$B$5),"Not modellable",IF(OR('Scenario Engine'!$D$14="Medicaid FFS",'Scenario Engine'!$D$14="Medicaid MCO"),IF('Payer Controls'!$B$38,"Moderate","Not modellable"),"Low")) -> Low | F26: =IF(NOT(Calculator!$B$5),"Not modellable",IF(AND(OR('Scenario Engine'!$D$14="Medicaid FFS",'Scenario Engine'!$D$14="Medicaid MCO"),'Scenario Engine'!$D$13="Yes",NOT('Payer Controls'!$B$39)),"Not modellable",IF(OR('Scenario Engine'!$D$13="Yes",'Scenario Engine'!$D$13="Unknown"),"Moderate","Low"))) -> Moderate | G26: =IF(NOT(Calculator!$B$5),"Not modellable",IF(OR('Scenario Engine'!$D$15="White-bagging",'Scenario Engine'!$D$15="Mixed"),"Moderate","Low")) -> Low | H26: =IF(NOT(Calculator!$B$5),"Not modellable",IF('Payer Controls'!$B$14<>"Yes","Moderate","Low")) -> Low
A28: Required caveats
A29: This scenario is for reimbursement planning only. It does not guarantee coverage, coding, payment, reimbursement, acquisition cost, provider margin, payer behavior, 340B pricing, pass-through status, HCPCS assignment, or claim outcome. Providers are responsible for verifying coding, billing, payer rules, contract terms, documentation, and institutional policy before claim submission.
A32: =IF('Scenario Engine'!$D$13="Yes","340B acquisition values are illustrative unless site-verified. This model does not guarantee 340B eligibility, 340B ceiling price, sub-ceiling price, provider acquisition cost, payer-recognized payment basis, or payer reimbursement outcome.","") -> 340B acquisition values are illustrative unless site-verified. This model does not guarantee 340B eligibility, 340B ceiling price, sub-ceiling price, provider acquisition cost, payer-recognized payment basis, or payer reimbursement outcome.
A35: This model assumes payer authorization has been approved for the patient, dose, frequency, site of care, and sourcing pathway reflected in the selected scenario. If authorization is pending, denied, under appeal, expired, or inconsistent with the modeled site/sourcing pathway, the economic output should not be used.

Sheet Source Register
A1: Policy and Assumption Source Register
A2: Source dates, owners, and field-use restrictions.
A3: Assumption ID | B3: Assumption name | C3: Value | D3: Category | E3: Source | F3: Source URL | G3: Source date | H3: Last reviewed | I3: Owner | J3: Field-use restriction
A4: SRC-001 | B4: HCPCS identifies items and services, not coverage/payment | C4: Coding status is separated from payment status. | D4: policy-backed rule | E4: CMS HCPCS Level II Coding Procedures | F4: https://www.cms.gov/medicare/coding/medhcpcsgeninfo/hcpcscodingprocess.html | G4: Page modified 2026-02-19; accessed 2026-05-02 | H4: 2026-05-02 | I4: Reimbursement strategy owner | J4: ARM-facing
A5: SRC-002 | B5: HCPCS quarterly drug/biological coding cycle | C5: Drug and biological code applications follow quarterly CMS review cycles. | D5: policy-backed rule | E5: CMS HCPCS Level II Coding Decisions | F5: https://www.cms.gov/medicare/coding-billing/healthcare-common-procedure-system/current-prior-years-level-ii-coding-decisions | G5: Accessed 2026-05-02 | H5: 2026-05-02 | I5: Reimbursement strategy owner | J5: ARM-facing
A6: SRC-003 | B6: OPPS pass-through is a payment pathway | C6: Pass-through status is modeled as payment status, not product coding status. | D6: policy-backed rule | E6: CMS Pass-Through Payment Status and New Technology APC | F6: https://www.cms.gov/Medicare/Medicare-Fee-for-Service-Payment/HospitalOutpatientPPS/passthrough_payment.html | G6: Accessed 2026-05-02 | H6: 2026-05-02 | I6: Reimbursement strategy owner | J6: ARM-facing
A7: SRC-004 | B7: Medicare Part B ASP/WAC branches | C7: ASP is primary for many Part B drugs; WAC may be used when ASP is unavailable. | D7: policy-backed rule | E7: CMS Part B Drugs and Biologicals | F7: https://www.cms.gov/cms-guide-medical-technology-companies-and-other-interested-parties/payment/part-b-drugs | G7: Page updated 2026-03-10; accessed 2026-05-02 | H7: 2026-05-02 | I7: Reimbursement strategy owner | J7: ARM-facing
A8: SRC-005 | B8: ASP pricing file caveat | C8: Presence or absence in CMS ASP files does not itself indicate coverage. | D8: policy-backed rule | E8: CMS ASP Pricing Files | F8: https://www.cms.gov/medicare/payment/part-b-drugs/asp-pricing-files | G8: Accessed 2026-05-02 | H8: 2026-05-02 | I8: Reimbursement strategy owner | J8: ARM-facing
A9: SRC-006 | B9: Medicaid PAD NDC/utilization requirements | C9: Medicaid PAD branches require NDC and utilization fields where applicable. | D9: policy-backed rule | E9: Medicaid.gov Physician Administered Drugs | F9: https://www.medicaid.gov/medicaid/prescription-drugs/state-prescription-drug-resources/physician-administered-drugs-pad | G9: Page updated 2022-10-20; accessed 2026-05-02 | H9: 2026-05-02 | I9: Medicaid policy owner | J9: ARM-facing
A10: SRC-007 | B10: MDRP 11-digit NDC data structure | C10: MDRP product and AMP files identify products using 11-digit NDCs. | D10: policy-backed rule | E10: Medicaid.gov MDRP Data | F10: https://www.medicaid.gov/medicaid/prescription-drugs/medicaid-drug-rebate-program/medicaid-drug-rebate-program-data | G10: Page updated 2026-04-13; accessed 2026-05-02 | H10: 2026-05-02 | I10: Medicaid policy owner | J10: ARM-facing
A11: SRC-008 | B11: 340B duplicate-discount prohibition | C11: Medicaid + 340B scenarios require duplicate-discount resolution before clean output. | D11: policy-backed rule | E11: HRSA Duplicate Discount Prohibition | F11: https://www.hrsa.gov/opa/program-requirements/medicaid-exclusion | G11: Accessed 2026-05-02 | H11: 2026-05-02 | I11: 340B/compliance owner | J11: ARM-facing
A12: SRC-009 | B12: 340B Medicaid Exclusion File applies to FFS | C12: MEF logic is not assumed to resolve Medicaid MCO plan requirements. | D12: policy-backed rule | E12: HRSA Medicaid Exclusion File help | F12: https://340bregistration.hrsa.gov/help/Manufacturer/Reports/MedicaidExclusionFile.htm | G12: Accessed 2026-05-02 | H12: 2026-05-02 | I12: 340B/compliance owner | J12: ARM-facing
A13: MOD-001 | B13: Adrabetadex launch WAC per vial | C13: $39,000 per 900 mg vial | D13: planning assumption | E13: Internal planning assumption | G13: 2026-05-02 | H13: 2026-05-02 | I13: Market access owner | J13: Internal only
A14: MOD-002 | B14: Primary 340B acquisition assumption | C14: Primary 23.1% planning assumption; site verification required | D14: planning assumption | E14: Internal planning assumption | G14: 2026-05-02 | H14: 2026-05-02 | I14: Market access owner | J14: Internal/ARM-facing

Sheet Test Cases
A1: Validation Test Cases
A2: Minimum gate and scenario-engine tests for go/no-go.
A3: Test ID | B3: Scenario | C3: Expected Result | D3: Validation Method | E3: Status | F3: Notes
A4: T01 | B4: PA not started | C4: Economics suppressed. | D4: Python validation + workbook inspection | E4: Run validate script | F4: PA gate message required.
A5: T02 | B5: PA pending | C5: Economics suppressed. | D5: Python validation + workbook inspection | E5: Run validate script | F5: Submitted/pending status.
A6: T03 | B6: PA denied/appeal | C6: Economics suppressed. | D6: Python validation + workbook inspection | E6: Run validate script | F6: Access workflow status, not economics.
A7: T04 | B7: PA approved, full scope match | C7: Economics calculated. | D7: Python validation + workbook inspection | E7: Run validate script | F7: Default S01.
A8: T05 | B8: PA approved, site-of-care mismatch | C8: Economics suppressed with warning. | D8: Python validation + workbook inspection | E8: Run validate script | F8: Authorized site differs.
A9: T06 | B9: PA approved, sourcing mismatch | C9: Economics suppressed with warning. | D9: Python validation + workbook inspection | E9: Run validate script | F9: Authorized sourcing differs.
A10: T07 | B10: PA approved, partial-year authorization | C10: Output limited to authorized doses; full-year projection labeled. | D10: Python validation + workbook inspection | E10: Run validate script | F10: Authorized doses less than annual administrations.
A11: T08 | B11: Medicaid FFS + missing NDC | C11: Medicaid economics suppressed or high-risk/not-modellable flag. | D11: Python validation + workbook inspection | E11: Run validate script | F11: NDC missing.
A12: T09 | B12: Medicaid + 340B + duplicate-discount unresolved | C12: Clean output suppressed or high-risk/not-modellable flag. | D12: Python validation + workbook inspection | E12: Run validate script | F12: Duplicate discount unresolved.
A13: T10 | B13: White-bagging scenario | C13: Drug spread set to zero or payer-specific value. | D13: Python validation + workbook inspection | E13: Run validate script | F13: S05 branch.
A14: T11 | B14: Manual override active | C14: Output visibly flags active override. | D14: Python validation + workbook inspection | E14: Run validate script | F14: Workbook active source formula.
... A17: T14 | B17: HOPD pass-through scenario | C17: OPPS pass-through branch used only if payment status is pass-through active. | D17: Python validation + workbook inspection | E17: Run validate script | F17: S01 branch.
